zadu/__init__.py
zadu/zadu.py
zadu/measures/__init__.py
zadu/measures/class_aware_trustworthiness_continuity.py
zadu/measures/clustering_and_external_validation_measure.py
zadu/measures/distance_consistency.py
zadu/measures/distance_to_measure.py
zadu/measures/internal_validation_measure.py
zadu/measures/kl_divergence.py
zadu/measures/label_trustworthiness_and_continuity.py
zadu/measures/local_continuity_meta_criteria.py
zadu/measures/mean_relative_rank_error.py
zadu/measures/neighbor_dissimilarity.py
zadu/measures/neighborhood_hit.py
zadu/measures/non_metric_stress.py
zadu/measures/pearson_r.py
zadu/measures/procrustes.py
zadu/measures/scale_normalized_stress.py
zadu/measures/spearman_rho.py
zadu/measures/steadiness_cohesiveness.py
zadu/measures/stress.py
zadu/measures/topographic_product.py
zadu/measures/trustworthiness_continuity.py
zadu/measures/utils/__init__.py
zadu/measures/utils/knn.py
zadu/measures/utils/label_cvms.py
zadu/measures/utils/pairwise_dist.py
zadu-0.3.0.dist-info/licenses/LICENSE
zaduvis/__init__.py
zaduvis/colormap.py
zaduvis/zaduvis.py
zadu-0.3.0.dist-info/METADATA
zadu-0.3.0.dist-info/WHEEL
zadu-0.3.0.dist-info/top_level.txt
zadu-0.3.0.dist-info/RECORD
