Metadata-Version: 2.4
Name: zadu
Version: 0.3.0
Summary: A Python Toolkit for Evaluating the Reliability of Dimensionality Reduction Embeddings
Home-page: https://github.com/hj-n/zadu
Author: Hyeon Jeon
Author-email: hj@hcil.snu.ac.kr
Classifier: Programming Language :: Python :: 3
Classifier: License :: OSI Approved :: MIT License
Classifier: Operating System :: OS Independent
Requires-Python: >=3.10.0
License-File: LICENSE
Requires-Dist: numpy
Requires-Dist: scikit-learn
Requires-Dist: scipy
Requires-Dist: snc
Requires-Dist: matplotlib
Requires-Dist: faiss-cpu
Dynamic: author
Dynamic: author-email
Dynamic: classifier
Dynamic: description
Dynamic: description-content-type
Dynamic: home-page
Dynamic: license-file
Dynamic: requires-dist
Dynamic: requires-python
Dynamic: summary
